8-ALU_Control/alu_control.v
`timescale 1ns / 1ps
//alu-control - ALU control: define type of ALU operation using func3,func7,opcode

module alu_control (clk,func3,func7,opcode,alu_control);
input clk;
input [2:0] func3;
input [6:0] func7;
input [6:0] opcode;
output reg [2:0] alu_control;

parameter r_type = 7'b0110011;//add,sub,and,or
parameter s_type = 7'b0100011;//sw,sb
parameter i_type = 7'b0010011;//addi
parameter l_type = 7'b0000011;//lw,lb
parameter b_type = 7'b1100011;//beq,bge,blt
parameter jal    = 7'b1101111;//jal
parameter jalr   = 7'b1100111;//jalr

always @(*) begin
    //Default value for debug
    alu_control=3'bx;
    
    case(opcode)
    r_type:
    begin
        if(func3==3'b111 && func7==7'b0)//And
            alu_control = 3'b000;
        else if(func3==3'b110 && func7==7'b0)//or
            alu_control = 3'b001;
        else if(func3==3'b0 && func7==7'b0)//Add
            alu_control = 3'b010;
        else if(func3==3'b0 && func7==7'b0100000)//Sub
            alu_control = 3'b011;
    end
    s_type:alu_control = 3'b010;
    i_type:alu_control = 3'b010;
    l_type:alu_control = 3'b010;
    b_type:
    begin
        if(func3==3'b100)//blt
            alu_control = 3'b100;

        else if(func3==3'b010)//bge
            alu_control = 3'b101;
            
        else if(func3==3'b000)//beq
            alu_control = 3'b110;

    end
    jal:alu_control = 3'b010;
    jalr:alu_control = 3'b010;
    endcase
end
endmodule

7-Alu_control/alu_control_tb.v
`include "alu_control.v"

module alu_control_tb ();
    //Inputs
    reg clk;
    reg [2:0] func3;
    reg [6:0] func7;
    reg [6:0] opcode;

    //Outputs
    wire [2:0] alu_control;

    alu_control uut (clk,func3,func7,opcode,alu_control);

    //Clock toggles every 5ns
    always#2 clk=~clk;

    initial begin
        $dumpfile("alu_control.vcd");
        $dumpvars(0,alu_control_tb);

        //Initialize inputs
        clk=0;#10

        opcode  = 7'b0110011;//r_type 
            func3=3'b111;func7=7'b0;#10//and
            func3=3'b110;func7=7'b0;#10//or
            func3=3'b0;func7=7'b0;#10//add
            func3=3'b0;func7=7'b0100000;#10//sub

        opcode  = 7'b0100011;#10//s_type = sw,sb
        opcode  = 7'b0010011;#10//i_type = addi
        opcode  = 7'b0000011;#10//type = lw,lb

        opcode  = 7'b1100011;//b-type
            func3=3'b100;#10//blt
            func3=3'b010;#10//bge
            func3=3'b0;#10//beq

        opcode  = 7'b1101111;#10//jal
        opcode  = 7'b1100111;#10//jalr

        $finish;
    end
endmodule

8-ALU_Control/alu_control.vcd
$date
	Thu May 25 16:26:20 2023
$end
$version
	Icarus Verilog
$end
$timescale
	1ps
$end
$scope module alu_control_tb $end
$var wire 3 ! alu_control [2:0] $end
$var reg 1 " clk $end
$var reg 3 # func3 [2:0] $end
$var reg 7 $ func7 [6:0] $end
$var reg 7 % opcode [6:0] $end
$scope module uut $end
$var wire 1 " clk $end
$var wire 3 & func3 [2:0] $end
$var wire 7 ' func7 [6:0] $end
$var wire 7 ( opcode [6:0] $end
$var reg 3 ) alu_control [2:0] $end
$upscope $end
$upscope $end
$enddefinitions $end
#0
$dumpvars
bx )
bx (
bx '
bx &
bx %
bx $
bx #
0"
bx !
$end
#2000
1"
#4000
0"
#6000
1"
#8000
0"
#10000
b0 !
b0 )
1"
b0 $
b0 '
b111 #
b111 &
b110011 %
b110011 (
#12000
0"
#14000
1"
#16000
0"
#18000
1"
#20000
b1 !
b1 )
0"
b110 #
b110 &
#22000
1"
#24000
0"
#26000
1"
#28000
0"
#30000
b10 !
b10 )
1"
b0 #
b0 &
#32000
0"
#34000
1"
#36000
0"
#38000
1"
#40000
b11 !
b11 )
0"
b100000 $
b100000 '
#42000
1"
#44000
0"
#46000
1"
#48000
0"
#50000
b10 !
b10 )
1"
b100011 %
b100011 (
#52000
0"
#54000
1"
#56000
0"
#58000
1"
#60000
b10 !
b10 )
0"
b10011 %
b10011 (
#62000
1"
#64000
0"
#66000
1"
#68000
0"
#70000
b10 !
b10 )
1"
b11 %
b11 (
#72000
0"
#74000
1"
#76000
0"
#78000
1"
#80000
b100 !
b100 )
0"
b100 #
b100 &
b1100011 %
b1100011 (
#82000
1"
#84000
0"
#86000
1"
#88000
0"
#90000
b101 !
b101 )
1"
b10 #
b10 &
#92000
0"
#94000
1"
#96000
0"
#98000
1"
#100000
b110 !
b110 )
0"
b0 #
b0 &
#102000
1"
#104000
0"
#106000
1"
#108000
0"
#110000
b10 !
b10 )
1"
b1101111 %
b1101111 (
#112000
0"
#114000
1"
#116000
0"
#118000
1"
#120000
b10 !
b10 )
0"
b1100111 %
b1100111 (
