1-PC/pc.v
`timescale 1ns / 1ps
//PC- Program Counter: for 1024B instruction memory

module pc(clk,reset,branch,mem_to_reg,immediate,reg_out1,pc_out);
input clk;		           	//clock
input reset;               	//reset whole circuit to default
input branch;              	//bool 0=nojump , 1=jump 
input [1:0] mem_to_reg;		// x=b_type, 2 = jal , 3 = jalr 

input [31:0] reg_out1;    	//Reg[rs1] from Reg File
input [20:0] immediate;  	//immediate -> max 21bits for J type

output reg [9:0] pc_out;	//10bit address -> 2^10 index -> 1024 bytes

always@(posedge clk)begin

	if(reset) 		//reset pc_output
		pc_out = 0;
	else if (branch && mem_to_reg==2'b11)	//jalr: PC = (rs1 + imm) 
		pc_out = immediate + reg_out1;
	else if(branch || mem_to_reg==2'b10) 	//b_type or jal: PC = PC + imm
		pc_out = pc_out + immediate;
	else    //no jump
		pc_out = pc_out + 4;
end
 
endmodule

1-PC/pc_tb.v
`include "pc.v"

module pc_tb;
    //Inputs
    reg clk,reset,branch;
    reg [1:0] mem_to_reg;
    reg [20:0] immediate;
    reg [31:0] reg_out1;

    //Outputs
    wire [9:0] pc_out;

    pc uut (clk,reset,branch,mem_to_reg,immediate,reg_out1,pc_out);

    //Clock toggles in 5ns
    always#5 clk=~clk;

    initial begin
        $dumpfile("pc.vcd");
        $dumpvars(0,pc_tb);

        //Reset
        clk = 0 ; reset = 1; #10
        reset=0;

        //PC+4
        branch = 0;#20

        //b_type or jal
        branch = 1;
        immediate = 196;#10
        mem_to_reg = 2;
        immediate = 800;#10

        //jalr
        branch = 1;
        mem_to_reg=3;reg_out1=15;
        immediate = 20;#10
        
        $finish;
    end
endmodule

1-PC/pc.vcd
$date
	Sun May 14 12:42:20 2023
$end
$version
	Icarus Verilog
$end
$timescale
	1ps
$end
$scope module pc_tb $end
$var wire 10 ! pc_out [9:0] $end
$var reg 1 " branch $end
$var reg 1 # clk $end
$var reg 21 $ immediate [20:0] $end
$var reg 2 % mem_to_reg [1:0] $end
$var reg 32 & reg_out1 [31:0] $end
$var reg 1 ' reset $end
$scope module uut $end
$var wire 1 " branch $end
$var wire 1 # clk $end
$var wire 21 ( immediate [20:0] $end
$var wire 2 ) mem_to_reg [1:0] $end
$var wire 32 * reg_out1 [31:0] $end
$var wire 1 ' reset $end
$var reg 10 + pc_out [9:0] $end
$upscope $end
$upscope $end
$enddefinitions $end
#0
$dumpvars
bx +
bx *
bx )
bx (
1'
bx &
bx %
bx $
0#
x"
bx !
$end
#5000
b0 !
b0 +
1#
#10000
0#
0"
0'
#15000
b100 !
b100 +
1#
#20000
0#
#25000
b1000 !
b1000 +
1#
#30000
0#
b11000100 $
b11000100 (
1"
#35000
b11001100 !
b11001100 +
1#
#40000
0#
b1100100000 $
b1100100000 (
b10 %
b10 )
#45000
b1111101100 !
b1111101100 +
1#
#50000
0#
b10100 $
b10100 (
b1111 &
b1111 *
b11 %
b11 )
#55000
b100011 !
b100011 +
1#
