10-Mux_mem_to_reg/mem_to_reg.v
`timescale 1ns / 1ps
//mem_to_reg- Memeory to Register MUX: select Alu output or Data read from 
//            Memory to write in register rd
//0 = Alu_output
//1 = data_mem_output
//2,3 = pc + 4

module mem_to_reg (clk,mem_to_reg,alu_result,mem_data,pc_4,selected);
input clk;                  //System clock
input [1:0] mem_to_reg;           //control signal from Control
input [31:0] alu_result;    //Reg[rs2] from Register File
input [31:0] mem_data;      //Immediate from Decoder
input [9:0] pc_4;          //pc from PC add 4 to it
output reg [31:0] selected; //MUX output

always @(posedge clk) begin
    if(mem_to_reg==1)
        selected = mem_data;
    else if (mem_to_reg==0)
        selected = alu_result;
    else if (mem_to_reg==2 || mem_to_reg==3)
        selected = pc_4 + 1;//pc + 1
end
endmodule

6-Data_Mem/data_mem.v
`timescale 1ns / 1ps
//data_mem- Data Memory: 1024byte memory for data

module data_mem (clk,size,mem_read,mem_write,address,data_in,data_out);
input clk;              //system clock
input size;             //size of data: 0=byte or 1=word
input mem_read;         //control to read data
input mem_write;        //control to write data
input [31:0] address;   //address to read/write 
input [31:0] data_in;   //input data for write
output reg [31:0] data_out; //output data for read

reg [7:0] memory [1023:0];  // Data memory ibyte x 1024 index = 1024 byte memory

always @(*) begin
    //Temp data for debug
    memory[0]=8'h0;
    memory[1]=8'h0;
    memory[2]=8'h1;
    memory[3]=8'h0;//h0100 = 256

    memory[4]=8'h0;
    memory[5]=8'ha;
    memory[6]=8'h0;
    memory[7]=8'h1;//h10a0 = 4256

    memory[8]=8'h0;
    memory[9]=8'h7;
    memory[10]=8'h2;
    memory[11]=8'h3;//h3270 = 12912

    //Logic
    case(size)
    0:      //byte
    begin
        if(mem_write)
            memory[address] = data_in;
        if(mem_read)
            data_out = memory[address];
    end
    1:
    begin
        if(mem_write)//write byte by byte
        begin
            memory[address] = data_in[7:0];
            memory[address+1] = data_in[15:8];
            memory[address+2] = data_in[23:16];
            memory[address+3] = data_in[31:24];
        end

        if(mem_read)//read byte by byte
        begin
            data_out[7:0] = memory[address];
            data_out[15:8] = memory[address+1]; 
            data_out[23:16] = memory[address+2]; 
            data_out[31:24] = memory[address+3];
        end
    end
    endcase

end

endmodule

5-ALU/alu.v
`timescale 1ns / 1ps
//alu- Arithmetic Logic Unit: perform operations based on ISA.txt
// 
// ALU control | Function
// -----------------------------
//         000    Bitwise-AND
//         001    Bitwise-OR
//         010	  Add (A+B)
//         011    Subtract (A-B)
//         100	  Less than (A<B)
//         101    Greater than or equal (A>=B)
//         110    Equal (A==B)
//         111    xxxxxxxx
module alu (clk,in1,in2,result,alu_control,zero_flag);
input clk;                      //sytem clock
input [31:0] in1,in2;           //data inputs
input[2:0] alu_control;         //control for operation selection
output reg [31:0] result;   //output of ALU
output reg zero_flag;                //flag if beq,blt,bge TRUE

always @(*) begin
        // Operating based on control input
        case(alu_control)

            3'b000: result = in1&in2; //AND
            3'b001: result = in1|in2; //OR
            3'b010: result = in1+in2; //Add
            3'b011: result = in1-in2; //Sub
            3'b100:                       //A<B
            begin 
                if(in1<in2)
                    result = 32'b0;
                else
                    result = 32'bx;
            end
            3'b101: 
            begin 
                if(in1>=in2)            //A>=B
                    result = 32'b0;
                else
                    result = 32'bx;
            end
            3'b011:                     //A==B
            begin 
                if(in1==in2)
                    result = 32'b0;
                else
                    result = 32'bx;
            end
        endcase

        // Setting Zero_flag if ALU_result is zero
        if (result == 32'b0)
            zero_flag = 1'b1;
        else
            zero_flag = 1'b0;
end
    
endmodule

9-Mux_alu_src/alu_src.v
`timescale 1ns / 1ps
//alu_src- ALU src MUX: select Reg[rs2] or imm for second ALU inputs
//0 = Reg[rs2]
//1 = imm

module alu_src (clk,alu_src,reg_out2,imm,selected);
input clk;                  //System clock
input alu_src;              //control signal from Control
input [31:0] reg_out2;      //Reg[rs2] from Register File
input [20:0] imm;           //Immediate from Decoder
output reg [31:0] selected; //MUX output

always @(posedge clk ) begin
    if(alu_src==1)
        selected = imm;
    else if (alu_src==0)
        selected = reg_out2;
end
endmodule

4-Reg_File/reg_file.v
`timescale 1ns / 1ps
//reg_file- Register File: stores the 32 registers

module reg_file (clk,reg_write,write_data,rs1,rs2,rd,out1,out2,reset);
input clk,reset;                  //system clock
input reg_write;            //0=read , 1=write
input [31:0] write_data;    //32bit data -> Reg[rd]=rwrite_data
input [4:0] rs1,rs2,rd;     //5bit reg address 
output [31:0] out1,out2;//32bit reg output -> out1,out2 = Reg[rs1],Reg[rs2]

reg [31:0] Reg [31:0];      //32 registers each 32bit

always @(posedge clk) begin
	//Temp data for debug
	Reg[1]=5;
	Reg[2]=6;
	Reg[3]=0;
	Reg[4]=6;
	Reg[5]=9;

    //Reg[0] is hardcoded 0
	Reg[0]=0;

    //Logic
    if(reg_write) 	//write to rd
		Reg[rd] = write_data;
end


//read rs1,rs2
assign	out1 = Reg[rs1];
assign	out2 = Reg[rs2];

endmodule

7-Alu_control/alu_control.v
`timescale 1ns / 1ps
//alu-control - ALU control: define type of ALU operation using func3,func7,opcode

module alu_control (clk,func3,func7,opcode,alu_control);
input clk;
input [2:0] func3;
input [6:0] func7;
input [6:0] opcode;
output reg [2:0] alu_control;

parameter r_type = 7'b0110011;//add,sub,and,or
parameter s_type = 7'b0100011;//sw,sb
parameter i_type = 7'b0010011;//addi
parameter l_type = 7'b0000011;//lw,lb
parameter b_type = 7'b1100011;//beq,bge,blt
parameter jal    = 7'b1101111;//jal
parameter jalr   = 7'b1100111;//jalr

always @(posedge clk ) begin
    case(opcode)
    r_type:
    begin
        if(func3==3'b111 && func7==7'b0)//And
            alu_control = 3'b000;
        else if(func3==3'b110 && func7==7'b0)//or
            alu_control = 3'b001;
        else if(func3==3'b0 && func7==7'b0)//Add
            alu_control = 3'b010;
        else if(func3==3'b0 && func7==7'b0100000)//Sub
            alu_control = 3'b011;
    end
    s_type:alu_control = 3'b010;
    i_type:alu_control = 3'b010;
    l_type:alu_control = 3'b010;
    b_type:
    begin
        if(func3==3'b100)//blt
            alu_control = 3'b100;

        else if(func3==3'b010)//bge
            alu_control = 3'b101;
            
        else if(func3==3'b000)//beq
            alu_control = 3'b110;

    end
    jal:alu_control = 3'b010;
    jalr:alu_control = 3'b010;
    endcase
end
endmodule

7-Control_Unit/control.v
`timescale 1ns / 1ps
//control- Control Unit: map opcode to control signals 

module control(clk,opcode,branch,mem_read,mem_write,alu_src,reg_write,mem_to_reg);
input clk;                  //System clock
input [6:0] opcode;         //opcode from instruction
output reg branch,mem_read,mem_write,alu_src,reg_write; //control signals
output reg [1:0] mem_to_reg;//control signal

parameter r_type = 7'b0110011;//add,sub,and,or
parameter s_type = 7'b0100011;//sw,sb
parameter i_type = 7'b0010011;//addi
parameter l_type = 7'b0000011;//lw,lb
parameter b_type = 7'b1100011;//beq,bge,blt
parameter jal    = 7'b1101111;//jal
parameter jalr   = 7'b1100111;//jalr


always @(*) begin
    case(opcode)
    r_type:
    begin
        alu_src = 0;
        mem_to_reg = 2'b00;
        reg_write = 1;
        mem_read = 0;
        mem_write = 0;
        branch = 0;
	end
    s_type:
    begin
        alu_src = 1;
        mem_to_reg = 2'bx;
        reg_write = 0;
        mem_read = 0;
        mem_write = 1;
        branch = 0;
	end
    i_type:
    begin
        alu_src = 0;
        mem_to_reg = 2'b0;
        reg_write = 1;
        mem_read = 0;
        mem_write = 0;
        branch = 0;
	end
    l_type:
    begin
        alu_src = 1;
        mem_to_reg = 2'b01;
        reg_write = 1;
        mem_read = 1;
        mem_write = 0;
        branch = 0;
	end
    b_type:
    begin
        alu_src = 0;
        mem_to_reg = 2'bx;
        reg_write = 0;
        mem_read = 0;
        mem_write = 0;
        branch = 1;
	end
    jal:
    begin
        alu_src = 0;
        mem_to_reg = 2'b10;
        reg_write = 1;
        mem_read = 0;
        mem_write = 0;
        branch = 1;
	end
    jalr:
    begin
        alu_src = 1;
        mem_to_reg = 2'b11;
        reg_write = 1;
        mem_read = 0;
        mem_write = 0;
        branch = 1;
	end
    endcase
end
endmodule

3-Decoder/decoder.v
`timescale 1ns / 1ps
//decoder- Decoder: split 32bit instruction into parts

module decoder (clk,instruction,func3,func7,opcode,rs1,rs2,rd,imm,size);
input clk;                  //System clock
input [31:0] instruction;   //instruction from instruction memory

output reg [2:0] func3;     
output reg [6:0] func7;  
output reg [6:0] opcode;    //opcode for control
output reg [4:0] rs1,rs2,rd;//read_reg1,read_reg2,write_reg
output reg [20:0] imm;      //immediate -> max 20bit for Jtype
output reg size;            //size of data: 0=byte , 1=word

parameter r_type = 7'b0110011;//add,sub,and,or
parameter s_type = 7'b0100011;//sw,sb
parameter i_type = 7'b0010011;//addi
parameter l_type = 7'b0000011;//lw,lb
parameter b_type = 7'b1100011;//beq,bge,blt
parameter jal    = 7'b1101111;//jal
parameter jalr   = 7'b1100111;//jalr

always @(*) begin
    opcode = instruction[6:0]; //all instructions have opcode
    size = 1;//default size is word

    //Make all outputs 0 by default -> no garbage data
    func3=0;func7=0;imm=0;rs1=0;rs2=0;rd=0;

    //all regs (size N) not used are turned to N'bx

    case(opcode)
    r_type:
    begin
        rd = instruction[11:7];
        func3 = instruction[14:12];
        rs1 = instruction[19:15];
        rs2 = instruction[24:20];
        func7 = instruction[31:25];
    end
    s_type:
    begin
        imm[4:0] = instruction[11:7];
        func3 = instruction[14:12];
        rs1 = instruction[19:15];
        rs2 = instruction[24:20];
        imm[11:5] = instruction[31:25];
        rd = 5'bx;
        func7 = 7'bx;

        if(func3 == 3'b000)//sb
            size=0;
    end
    i_type:
    begin
        rd = instruction[11:7];
        func3 = instruction[14:12];
        rs1 = instruction[19:15];
        rs2 = instruction[24:20];
        imm[11:0] = instruction[31:25];
        func7 = 7'bx;
    end
    l_type:
    begin
        rd = instruction[11:7];
        func3 = instruction[14:12];
        rs1 = instruction[19:15];
        rs2 = instruction[24:20];
        imm[11:0] = instruction[31:25];
        func7 = 7'bx;

        if(func3 == 3'b000)//lb
            size=0;
    end
    b_type://shift right one
    begin
        imm[11] = instruction[7];
        imm[4:1] = instruction[11:8];
        func3 = instruction[14:12];
        rs1 = instruction[19:15];
        rs2 = instruction[24:20];
        imm[10:5] = instruction[30:25];
        imm[12] = instruction[31];
        //imm is arranged [12,11,10:5,4:1] and sign right shifted 1
        imm = imm>>>1;

        rd = 5'bx;
        func7 = 7'bx;
    end
    jal:
    begin
        rd = instruction[11:7];
        imm[19:12] = instruction[19:12];
        imm[11] = instruction[20];
        imm[10:1] = instruction[30:21];
        imm[20] = instruction[31];
        //imm is arranged [20,19:12,11,10:1] and sign right shifted 1
        imm = imm>>>1;

        func3=3'bx;
        rs1=5'bx;
        rs2=5'bx;
        func7=7'bx;
    end
    jalr:
    begin
        rd = instruction[11:7];
        func3 = instruction[14:12];
        rs1 = instruction[19:15];
        rs2 = instruction[24:20];
        imm[11:0] = instruction[31:25];
        func7 = 7'bx;
    end
    endcase
end

endmodule

2-Insn_Mem/insn_mem.v
`timescale 1ns / 1ps
//insn_mem- Instruction Memory: 32bit x 1024 index memory for instruction

module insn_mem(clk,insn_out,pc_out);
input clk;                      //system clock
input [9:0] pc_out;             //instruction index from pc
output reg [31:0] insn_out;     //output instruction 

reg [31:0] memory [1023:0];   //32bit x 1024index memory

always@(*)begin
    //fill with instructions
    memory[0] = 32'b00000000001000001000000010110011;   // add x1 x1 x2
    memory[1] = 32'b01000000001100010000000100110011;   // sub x2 x2 x3
    memory[2] = 32'b00000000000100100111001000110011;   // and x4 x4 x1
    memory[3] = 32'b00000000010100011110000110110011;   // or x3 x3 x5

    memory[4] = 32'b00000000110000010000001000010011;   // addi x4 x2 12

    memory[5] = 32'b00000000000000000010000110000011;   // lw x3 0(x0)
    memory[6] = 32'b00000000010100001000001010000011;   // lb x5 5(x1)

    memory[7] = 32'b00000000010100011010001010100011;   // sw x5 5(x3)
    memory[8] = 32'b0000000000100001000110100100011;   // sb x6 90(x1)

    memory[9] = 32'b00000001000000010000001001100011;   // beq x4 x2 26
    memory[10] = 32'b00000001000000010101000101100011;   // bge x2 x2 26
    memory[11] = 32'b00000001000000010100010001100011;   // blt x8 x2 26

    memory[12] = 32'b00000001100000000000000101101111; // jal x2 12

    //mem[24] b/c of jal jump : 12+12
    memory[24] = 32'b00000000011000001000000101100111; // jalr x2 x1 6 


    //output instruction at pc_out address
    insn_out = memory[pc_out]; 
end


endmodule

1-PC/pc.v
`timescale 1ns / 1ps
//PC- Program Counter: for 1024B instruction memory

module pc(clk,reset,branch,zero_flag,mem_to_reg,immediate,reg_out1,pc_out);
input clk;		           	//clock
input reset;               	//reset whole circuit to default
input branch;              	//bool 0=nojump , 1=jump 
input zero_flag;			//flag = 0 if beq,blt,bge is True

input [1:0] mem_to_reg;		// x=b_type, 2 = jal , 3 = jalr 

input [31:0] reg_out1;    	//Reg[rs1] from Reg File
input [20:0] immediate;  	//immediate -> max 21bits for J type

output reg [9:0] pc_out;	//10bit address -> 2^10 index -> 1024 bytes

always@(posedge clk)begin

	if(reset) 		//reset pc_output
		pc_out = 0;

	else if(branch && zero_flag && mem_to_reg==2'bx) 			//b_type: PC = PC + imm
		pc_out = pc_out + immediate;

	else if(branch && mem_to_reg==2'b10) 	//al: PC = PC + imm
		pc_out = pc_out + immediate;

	else if (branch && mem_to_reg==2'b11)	//jalr: PC = (rs1 + imm) 
		pc_out = immediate + reg_out1;
		
	else    		//no jump
		pc_out = pc_out + 4;
end
 
endmodule

PROCESSOR/processor.v
`include "../1-PC/pc.v"
`include "../2-Insn_Mem/insn_mem.v"
`include "../3-Decoder/decoder.v"
`include "../4-Reg_File/reg_file.v"
`include "../5-ALU/alu.v"
`include "../6-Data_Mem/data_mem.v"
`include "../7-Control_Unit/control.v"
`include "../8-ALU_Control/alu_control.v"
`include "../9-Mux_alu_src/alu_src.v"
`include "../10-Mux_mem_to_reg/mem_to_reg.v"

module processor (clk,reset,pc,insn,imm_out,alu_control,reg_out1,reg_out2,alu_result,flag,read_data);
input clk;          //System clock

//Processor output -> for Testing
output [9:0] pc;            //PC
output [31:0] insn;         //Reg file
output [20:0] imm_out;      //Decoder
output [2:0] alu_control;   //Alu control
output [31:0] reg_out1;     //Reg File
output [31:0] reg_out2;     //Reg File
output [31:0] alu_result;   //ALU
output flag;                //ALU
output [31:0] read_data;    //Data memory

assign pc = pc_out;
assign insn = insn_out; 
assign imm_out = imm;
assign alu_control = alu_op;
assign reg_out1 = out1;
assign reg_out2 = out2;
assign alu_result = result;
assign flag = zero_flag;
assign read_data = data_out;
//---------------------------------------------------------------------------------------

//PC inputs
input reset;
// input branch;        -> outputs of other modules
// input zero_flag;      
// input [1:0] mem_to_reg;
// input [20:0] immediate;
// input [31:0] reg_out1;


//PC outputs 
wire [9:0] pc_out;  // -> insn mem

pc Pc(clk,reset,branch,zero_flag,mem_to_reg,imm,out1,pc_out);
//-------------------------------------------

//Instruction Memory output 
wire [31:0] insn_out;   // -> decoder

insn_mem Instruction_Memory(clk,insn_out,pc_out);
//-------------------------------------------

//Decoder output 
wire [2:0] func3; 
wire [6:0] func7;
wire [6:0] opcode;  // -> control , alu_control
wire [4:0] rs1;  
wire [4:0] rs2;
wire [4:0] rd;      // -> reg file
wire [20:0] imm;    // -> pc 
wire size;          // -> data mem

decoder Decoder(clk,insn_out,func3,func7,opcode,rs1,rs2,rd,imm,size);
//-------------------------------------------

//Control outputs
wire branch;        // -> pc
wire mem_read;
wire mem_write;     // -> data mem
wire alu_src;       // -> mux alu src
wire reg_write;     // -> reg file
wire [1:0] mem_to_reg; // -> pc, mux mem to reg

control Control_Unit(clk,opcode,branch,mem_read,mem_write,alu_src,reg_write,mem_to_reg);
//-------------------------------------------


//ALU control outputs
wire [2:0] alu_op;

alu_control ALU_COntrol(clk,func3,func7,opcode,alu_op);
//-------------------------------------------


//Reg File outputs
wire [31:0] out1;
wire [31:0] out2;

reg_file REGISTER_FILE(clk,reg_write,write_data,rs1,rs2,rd,out1,out2,reset);
//-------------------------------------------


//Mux alu src outputs
wire [31:0] selected;

alu_src MUX_ALU_src(clk,alu_src,out2,imm,selected); 
//-------------------------------------------


//ALU outputs
wire zero_flag;
wire [31:0] result;

alu ALU(clk,out1,selected,result,alu_op,zero_flag);
//-------------------------------------------

//DATA Memory outputs
//address = result -> from ALU
//data_in = out2 -> from reg file
wire [31:0] data_out;

data_mem Data_Memory(clk,size,mem_read,mem_write,result,selected,data_out);
//-------------------------------------------

//Mux mem to reg outputs
//pc_3 = pc_out -> from PC
//selected = write_data -> to Reg File
wire [31:0] write_data;

mem_to_reg Mem_to_Reg(clk,mem_to_reg,result,data_out,pc_out,write_data);
//-------------------------------------------

endmodule

PROCESSOR/processor_tb.v
`include "processor.v"

module processor_tb ();
    //Inputs
    reg clk,reset;

    //Outputs
    wire [9:0] pc;
    wire [31:0] insn;
    wire [20:0] imm_out;
    wire [2:0] alu_control;
    wire [31:0] reg_out1;
    wire [31:0] reg_out2;
    wire [31:0] alu_result;
    wire [31:0] read_data;
    wire flag;

    processor uut (clk,reset,pc,insn,imm_out,alu_control,reg_out1,reg_out2,alu_result,flag,read_data);

    //Clock toggles every 5ns
    always#5 clk=~clk;

    initial begin
        $dumpfile("processor.vcd");
        $dumpvars(0,processor_tb);
        //Initialize
        clk=0;reset=1;#10
        reset=0;

        #140 // 14 cycles

        $finish;
    end
endmodule

PROCESSOR/processor.vcd
$date
	Sun May 14 22:51:44 2023
$end
$version
	Icarus Verilog
$end
$timescale
	1ps
$end
$scope module processor_tb $end
$var wire 32 ! reg_out2 [31:0] $end
$var wire 32 " reg_out1 [31:0] $end
$var wire 32 # read_data [31:0] $end
$var wire 10 $ pc [9:0] $end
$var wire 32 % insn [31:0] $end
$var wire 21 & imm_out [20:0] $end
$var wire 1 ' flag $end
$var wire 32 ( alu_result [31:0] $end
$var wire 3 ) alu_control [2:0] $end
$var reg 1 * clk $end
$var reg 1 + reset $end
$scope module uut $end
$var wire 3 , alu_control [2:0] $end
$var wire 32 - alu_result [31:0] $end
$var wire 1 * clk $end
$var wire 1 ' flag $end
$var wire 21 . imm_out [20:0] $end
$var wire 32 / insn [31:0] $end
$var wire 10 0 pc [9:0] $end
$var wire 32 1 read_data [31:0] $end
$var wire 32 2 reg_out1 [31:0] $end
$var wire 32 3 reg_out2 [31:0] $end
$var wire 1 + reset $end
$var wire 1 4 zero_flag $end
$var wire 32 5 write_data [31:0] $end
$var wire 1 6 size $end
$var wire 32 7 selected [31:0] $end
$var wire 5 8 rs2 [4:0] $end
$var wire 5 9 rs1 [4:0] $end
$var wire 32 : result [31:0] $end
$var wire 1 ; reg_write $end
$var wire 5 < rd [4:0] $end
$var wire 10 = pc_out [9:0] $end
$var wire 32 > out2 [31:0] $end
$var wire 32 ? out1 [31:0] $end
$var wire 7 @ opcode [6:0] $end
$var wire 1 A mem_write $end
$var wire 2 B mem_to_reg [1:0] $end
$var wire 1 C mem_read $end
$var wire 32 D insn_out [31:0] $end
$var wire 21 E imm [20:0] $end
$var wire 7 F func7 [6:0] $end
$var wire 3 G func3 [2:0] $end
$var wire 32 H data_out [31:0] $end
$var wire 1 I branch $end
$var wire 1 J alu_src $end
$var wire 3 K alu_op [2:0] $end
$scope module ALU $end
$var wire 1 * clk $end
$var wire 32 L in2 [31:0] $end
$var wire 32 M in1 [31:0] $end
$var wire 3 N alu_control [2:0] $end
$var reg 32 O result [31:0] $end
$var reg 1 4 zero_flag $end
$upscope $end
$scope module ALU_COntrol $end
$var wire 1 * clk $end
$var wire 7 P opcode [6:0] $end
$var wire 7 Q func7 [6:0] $end
$var wire 3 R func3 [2:0] $end
$var reg 3 S alu_control [2:0] $end
$upscope $end
$scope module Control_Unit $end
$var wire 1 * clk $end
$var wire 7 T opcode [6:0] $end
$var reg 1 J alu_src $end
$var reg 1 I branch $end
$var reg 1 C mem_read $end
$var reg 2 U mem_to_reg [1:0] $end
$var reg 1 A mem_write $end
$var reg 1 ; reg_write $end
$upscope $end
$scope module Data_Memory $end
$var wire 32 V address [31:0] $end
$var wire 1 * clk $end
$var wire 1 C mem_read $end
$var wire 1 A mem_write $end
$var wire 1 6 size $end
$var wire 32 W data_in [31:0] $end
$var reg 32 X data_out [31:0] $end
$upscope $end
$scope module Decoder $end
$var wire 1 * clk $end
$var wire 32 Y instruction [31:0] $end
$var reg 3 Z func3 [2:0] $end
$var reg 7 [ func7 [6:0] $end
$var reg 21 \ imm [20:0] $end
$var reg 7 ] opcode [6:0] $end
$var reg 5 ^ rd [4:0] $end
$var reg 5 _ rs1 [4:0] $end
$var reg 5 ` rs2 [4:0] $end
$var reg 1 6 size $end
$upscope $end
$scope module Instruction_Memory $end
$var wire 1 * clk $end
$var wire 10 a pc_out [9:0] $end
$var reg 32 b insn_out [31:0] $end
$upscope $end
$scope module MUX_ALU_src $end
$var wire 1 J alu_src $end
$var wire 1 * clk $end
$var wire 21 c imm [20:0] $end
$var wire 32 d reg_out2 [31:0] $end
$var reg 32 e selected [31:0] $end
$upscope $end
$scope module Mem_to_Reg $end
$var wire 32 f alu_result [31:0] $end
$var wire 1 * clk $end
$var wire 32 g mem_data [31:0] $end
$var wire 2 h mem_to_reg [1:0] $end
$var wire 10 i pc_4 [9:0] $end
$var reg 32 j selected [31:0] $end
$upscope $end
$scope module Pc $end
$var wire 1 I branch $end
$var wire 1 * clk $end
$var wire 21 k immediate [20:0] $end
$var wire 2 l mem_to_reg [1:0] $end
$var wire 1 + reset $end
$var wire 1 4 zero_flag $end
$var wire 32 m reg_out1 [31:0] $end
$var reg 10 n pc_out [9:0] $end
$upscope $end
$scope module REGISTER_FILE $end
$var wire 1 * clk $end
$var wire 32 o out1 [31:0] $end
$var wire 32 p out2 [31:0] $end
$var wire 5 q rd [4:0] $end
$var wire 1 ; reg_write $end
$var wire 1 + reset $end
$var wire 5 r rs1 [4:0] $end
$var wire 5 s rs2 [4:0] $end
$var wire 32 t write_data [31:0] $end
$upscope $end
$upscope $end
$upscope $end
$enddefinitions $end
#0
$dumpvars
bx t
bx s
bx r
bx q
bx p
bx o
bx n
bx m
bx l
bx k
bx j
bx i
bx h
bx g
bx f
bx e
bx d
bx c
bx b
bx a
bx `
bx _
bx ^
bx ]
bx \
bx [
bx Z
bx Y
bx X
bx W
bx V
bx U
bx T
bx S
bx R
bx Q
bx P
bx O
bx N
bx M
bx L
bx K
xJ
xI
bx H
bx G
bx F
bx E
bx D
xC
bx B
xA
bx @
bx ?
bx >
bx =
bx <
x;
bx :
bx 9
bx 8
bx 7
x6
bx 5
x4
bx 3
bx 2
bx 1
bx 0
bx /
bx .
bx -
bx ,
1+
0*
bx )
bx (
x'
bx &
bx %
bx $
bx #
bx "
bx !
$end
#5000
0'
04
b1011 (
b1011 -
b1011 :
b1011 O
b1011 V
b1011 f
b110 7
b110 L
b110 W
b110 e
b10 )
b10 ,
b10 K
b10 N
b10 S
0I
0A
0C
1;
b0 B
b0 U
b0 h
b0 l
0J
b0 F
b0 Q
b0 [
b110 !
b110 3
b110 >
b110 d
b110 p
b101 "
b101 2
b101 ?
b101 M
b101 m
b101 o
b1 9
b1 _
b1 r
b0 G
b0 R
b0 Z
b1 <
b1 ^
b1 q
b10 8
b10 `
b10 s
b0 &
b0 .
b0 E
b0 \
b0 c
b0 k
16
b110011 @
b110011 P
b110011 T
b110011 ]
b1000001000000010110011 %
b1000001000000010110011 /
b1000001000000010110011 D
b1000001000000010110011 Y
b1000001000000010110011 b
b0 $
b0 0
b0 =
b0 a
b0 i
b0 n
1*
#10000
0*
0+
#15000
b1 7
b1 L
b1 W
b1 e
b11 )
b11 ,
b11 K
b11 N
b11 S
b10 <
b10 ^
b10 q
b1 !
b1 3
b1 >
b1 d
b1 p
b11 8
b11 `
b11 s
b10 9
b10 _
b10 r
b100000 F
b100000 Q
b100000 [
b0 G
b0 R
b0 Z
b101 (
b101 -
b101 :
b101 O
b101 V
b101 f
b1000000001100010000000100110011 %
b1000000001100010000000100110011 /
b1000000001100010000000100110011 D
b1000000001100010000000100110011 Y
b1000000001100010000000100110011 b
b1011 5
b1011 j
b1011 t
b110 "
b110 2
b110 ?
b110 M
b110 m
b110 o
b1 $
b1 0
b1 =
b1 a
b1 i
b1 n
1*
#20000
0*
#25000
b101 7
b101 L
b101 W
b101 e
1'
14
b0 )
b0 ,
b0 K
b0 N
b0 S
b100 <
b100 ^
b100 q
b101 !
b101 3
b101 >
b101 d
b101 p
b1 8
b1 `
b1 s
b100 9
b100 _
b100 r
b0 F
b0 Q
b0 [
b111 G
b111 R
b111 Z
b100100111001000110011 %
b100100111001000110011 /
b100100111001000110011 D
b100100111001000110011 Y
b100100111001000110011 b
b0 (
b0 -
b0 :
b0 O
b0 V
b0 f
b10 $
b10 0
b10 =
b10 a
b10 i
b10 n
b10 "
b10 2
b10 ?
b10 M
b10 m
b10 o
b101 5
b101 j
b101 t
1*
#30000
0*
#35000
b1011 7
b1011 L
b1011 W
b1011 e
b1 )
b1 ,
b1 K
b1 N
b1 S
b11 <
b11 ^
b11 q
b1011 !
b1011 3
b1011 >
b1011 d
b1011 p
b101 8
b101 `
b101 s
b11 9
b11 _
b11 r
b0 F
b0 Q
b0 [
b110 G
b110 R
b110 Z
0'
04
b1011 (
b1011 -
b1011 :
b1011 O
b1011 V
b1011 f
b10100011110000110110011 %
b10100011110000110110011 /
b10100011110000110110011 D
b10100011110000110110011 Y
b10100011110000110110011 b
b0 5
b0 j
b0 t
b1 "
b1 2
b1 ?
b1 M
b1 m
b1 o
b11 $
b11 0
b11 =
b11 a
b11 i
b11 n
1*
#40000
0*
#45000
bx 7
bx L
bx W
bx e
bx (
bx -
bx :
bx O
bx V
bx f
b10 )
b10 ,
b10 K
b10 N
b10 S
b1100 &
b1100 .
b1100 E
b1100 \
b1100 c
b1100 k
b100 <
b100 ^
b100 q
bx !
bx 3
bx >
bx d
bx p
b0xxx 8
b0xxx `
b0xxx s
b10 9
b10 _
b10 r
bx F
bx Q
bx [
b0 G
b0 R
b0 Z
b10011 @
b10011 P
b10011 T
b10011 ]
b110000010000001000010011 %
b110000010000001000010011 /
b110000010000001000010011 D
b110000010000001000010011 Y
b110000010000001000010011 b
b100 $
b100 0
b100 =
b100 a
b100 i
b100 n
b110 "
b110 2
b110 ?
b110 M
b110 m
b110 o
b1011 5
b1011 j
b1011 t
1*
#50000
0*
#55000
b10000000000000000 #
b10000000000000000 1
b10000000000000000 H
b10000000000000000 X
b10000000000000000 g
1'
14
b0 (
b0 -
b0 :
b0 O
b0 V
b0 f
b0 7
b0 L
b0 W
b0 e
b10 )
b10 ,
b10 K
b10 N
b10 S
1C
b1 B
b1 U
b1 h
b1 l
1J
b11 <
b11 ^
b11 q
b0 "
b0 2
b0 ?
b0 M
b0 m
b0 o
b0 9
b0 _
b0 r
b0 &
b0 .
b0 E
b0 \
b0 c
b0 k
b10 G
b10 R
b10 Z
b11 @
b11 P
b11 T
b11 ]
b10000110000011 %
b10000110000011 /
b10000110000011 D
b10000110000011 Y
b10000110000011 b
bx 5
bx j
bx t
b101 $
b101 0
b101 =
b101 a
b101 i
b101 n
1*
#60000
0*
#65000
b10 #
b10 1
b10 H
b10 X
b10 g
b101 7
b101 L
b101 W
b101 e
0'
04
b1010 (
b1010 -
b1010 :
b1010 O
b1010 V
b1010 f
b10 )
b10 ,
b10 K
b10 N
b10 S
06
b101 &
b101 .
b101 E
b101 \
b101 c
b101 k
b101 <
b101 ^
b101 q
b101 "
b101 2
b101 ?
b101 M
b101 m
b101 o
b1 9
b1 _
b1 r
b0 G
b0 R
b0 Z
b10100001000001010000011 %
b10100001000001010000011 /
b10100001000001010000011 D
b10100001000001010000011 Y
b10100001000001010000011 b
b110 $
b110 0
b110 =
b110 a
b110 i
b110 n
b10000000000000000 5
b10000000000000000 j
b10000000000000000 t
1*
#70000
0*
#75000
b110 (
b110 -
b110 :
b110 O
b110 V
b110 f
b10 )
b10 ,
b10 K
b10 N
b10 S
1A
0C
0;
bx B
bx U
bx h
bx l
b10000000000000000 !
b10000000000000000 3
b10000000000000000 >
b10000000000000000 d
b10000000000000000 p
b101 8
b101 `
b101 s
bx <
bx ^
bx q
b1 "
b1 2
b1 ?
b1 M
b1 m
b1 o
b11 9
b11 _
b11 r
b101 &
b101 .
b101 E
b101 \
b101 c
b101 k
b10 G
b10 R
b10 Z
16
b100011 @
b100011 P
b100011 T
b100011 ]
b10100011010001010100011 %
b10100011010001010100011 /
b10100011010001010100011 D
b10100011010001010100011 Y
b10100011010001010100011 b
b10 5
b10 j
b10 t
b111 $
b111 0
b111 =
b111 a
b111 i
b111 n
1*
#80000
0*
#85000
b11111 (
b11111 -
b11111 :
b11111 O
b11111 V
b11111 f
b11010 7
b11010 L
b11010 W
b11010 e
b10 )
b10 ,
b10 K
b10 N
b10 S
06
b1 8
b1 `
b1 s
b101 "
b101 2
b101 ?
b101 M
b101 m
b101 o
b1 9
b1 _
b1 r
b11010 &
b11010 .
b11010 E
b11010 \
b11010 c
b11010 k
b0 G
b0 R
b0 Z
b100001000110100100011 %
b100001000110100100011 /
b100001000110100100011 D
b100001000110100100011 Y
b100001000110100100011 b
b1000 $
b1000 0
b1000 =
b1000 a
b1000 i
b1000 n
b101 !
b101 3
b101 >
b101 d
b101 p
1*
#90000
0*
