3-Decoder/decoder.v
`timescale 1ns / 1ps
//decoder- Decoder: split 32bit instruction into parts

module decoder (clk,instruction,func3,func7,opcode,rs1,rs2,rd,imm,size);
input clk;                  //System clock
input [31:0] instruction;   //instruction from instruction memory

output reg [2:0] func3;     
output reg [6:0] func7;  
output reg [6:0] opcode;    //opcode for control
output reg [4:0] rs1,rs2,rd;//read_reg1,read_reg2,write_reg
output reg [20:0] imm;      //immediate -> max 20bit for Jtype
output reg size;            //size of data: 0=byte , 1=word

parameter r_type = 7'b0110011;//add,sub,and,or
parameter s_type = 7'b0100011;//sw,sb
parameter i_type = 7'b0010011;//addi
parameter l_type = 7'b0000011;//lw,lb
parameter b_type = 7'b1100011;//beq,bge,blt
parameter jal    = 7'b1101111;//jal
parameter jalr   = 7'b1100111;//jalr

always @(posedge clk ) begin
    opcode = instruction[6:0]; //all instructions have opcode
    size = 1;//default size is word

    //Make all outputs 0 by default -> no garbage data
    func3=0;func7=0;imm=0;rs1=0;rs2=0;rd=0;

    //all regs (size N) not used are turned to N'bx

    case(opcode)
    r_type:
    begin
        rd = instruction[11:7];
        func3 = instruction[14:12];
        rs1 = instruction[19:15];
        rs2 = instruction[24:20];
        func7 = instruction[31:25];
    end
    s_type:
    begin
        imm[4:0] = instruction[11:7];
        func3 = instruction[14:12];
        rs1 = instruction[19:15];
        rs2 = instruction[24:20];
        imm[11:5] = instruction[31:25];
        rd = 5'bx;
        func7 = 7'bx;

        if(func3 == 3'b000)//sb
            size=0;
    end
    i_type:
    begin
        rd = instruction[11:7];
        func3 = instruction[14:12];
        rs1 = instruction[19:15];
        rs2 = instruction[24:20];
        imm[11:0] = instruction[31:25];
        func7 = 7'bx;
    end
    l_type:
    begin
        rd = instruction[11:7];
        func3 = instruction[14:12];
        rs1 = instruction[19:15];
        rs2 = instruction[24:20];
        imm[11:0] = instruction[31:25];
        func7 = 7'bx;

        if(func3 == 3'b000)//lb
            size=0;
    end
    b_type://shift right one
    begin
        imm[11] = instruction[7];
        imm[4:1] = instruction[11:8];
        func3 = instruction[14:12];
        rs1 = instruction[19:15];
        rs2 = instruction[24:20];
        imm[10:5] = instruction[30:25];
        imm[12] = instruction[31];
        //imm is arranged [12,11,10:5,4:1] and sign right shifted 1
        imm = imm>>>1;

        rd = 5'bx;
        func7 = 7'bx;
    end
    jal:
    begin
        rd = instruction[11:7];
        imm[19:12] = instruction[19:12];
        imm[11] = instruction[20];
        imm[10:1] = instruction[30:21];
        imm[20] = instruction[31];
        //imm is arranged [20,19:12,11,10:1] and sign right shifted 1
        imm = imm>>>1;

        func3=3'bx;
        rs1=5'bx;
        rs2=5'bx;
        func7=7'bx;
    end
    jalr:
    begin
        rd = instruction[11:7];
        func3 = instruction[14:12];
        rs1 = instruction[19:15];
        rs2 = instruction[24:20];
        imm[11:0] = instruction[31:25];
        func7 = 7'bx;
    end
    endcase
end

endmodule

3-Decoder/decoder_tb.v
`include "decoder.v"

module decoder_tb ();
    //Inputs
    reg clk;
    reg [31:0] instruction;

    //Outputs
    wire [2:0] func3;     
    wire [6:0] func7;  
    wire [6:0] opcode;    
    wire [4:0] rs1;
    wire [4:0] rs2;
    wire [4:0] rd;
    wire [20:0] imm;     
    wire size; 

    decoder uut (clk,instruction,func3,func7,opcode,rs1,rs2,rd,imm,size);

    //Clock toggles every 5ns
    always#5 clk=~clk;

    initial begin
        $dumpfile("decoder.vcd");
        $dumpvars(0,decoder_tb);

        //Initialize inputs
        clk=0;#10

        instruction = 32'b00000000001000001000000010110011;#10 // add x1 x1 x2
        instruction = 32'b00000000001000001000000011100011;#10 // beq x1 x2 2048
        instruction = 32'b00000000000010000000000011101111;#10 // jal x1 262144
        instruction = 32'b00000000001000001000010000100011;#10 // sw x2 , 8(x1)

        $finish;
    end
endmodule

3-Decoder/decoder.vcd
$date
	Sun May 14 14:42:02 2023
$end
$version
	Icarus Verilog
$end
$timescale
	1ps
$end
$scope module decoder_tb $end
$var wire 1 ! size $end
$var wire 5 " rs2 [4:0] $end
$var wire 5 # rs1 [4:0] $end
$var wire 5 $ rd [4:0] $end
$var wire 7 % opcode [6:0] $end
$var wire 21 & imm [20:0] $end
$var wire 7 ' func7 [6:0] $end
$var wire 3 ( func3 [2:0] $end
$var reg 1 ) clk $end
$var reg 32 * instruction [31:0] $end
$scope module uut $end
$var wire 1 ) clk $end
$var wire 32 + instruction [31:0] $end
$var reg 3 , func3 [2:0] $end
$var reg 7 - func7 [6:0] $end
$var reg 21 . imm [20:0] $end
$var reg 7 / opcode [6:0] $end
$var reg 5 0 rd [4:0] $end
$var reg 5 1 rs1 [4:0] $end
$var reg 5 2 rs2 [4:0] $end
$var reg 1 ! size $end
$upscope $end
$upscope $end
$enddefinitions $end
#0
$dumpvars
bx 2
bx 1
bx 0
bx /
bx .
bx -
bx ,
bx +
bx *
0)
bx (
bx '
bx &
bx %
bx $
bx #
bx "
x!
$end
#5000
b0 $
b0 0
b0 "
b0 2
b0 #
b0 1
b0 &
b0 .
b0 '
b0 -
b0 (
b0 ,
1!
1)
#10000
0)
b1000001000000010110011 *
b1000001000000010110011 +
#15000
b10 "
b10 2
b1 #
b1 1
b1 $
b1 0
b110011 %
b110011 /
1)
#20000
0)
b1000001000000011100011 *
b1000001000000011100011 +
#25000
bx '
bx -
b10000000000 &
b10000000000 .
bx $
bx 0
b10 "
b10 2
b1 #
b1 1
b1100011 %
b1100011 /
1)
#30000
0)
b10000000000011101111 *
b10000000000011101111 +
#35000
bx (
bx ,
b1 $
b1 0
bx "
bx 2
bx #
bx 1
b1000000000000000000 &
b1000000000000000000 .
bx '
bx -
b1101111 %
b1101111 /
1)
#40000
0)
b1000001000010000100011 *
b1000001000010000100011 +
#45000
0!
bx $
bx 0
b10 "
b10 2
b1 #
b1 1
b1000 &
b1000 .
bx '
bx -
b0 (
b0 ,
b100011 %
b100011 /
1)
