10-Mux_mem_to_reg/mem_to_reg.v
`timescale 1ns / 1ps
//mem_to_reg- Memeory to Register MUX: select Alu output or Data read from 
//            Memory to write in register rd
//0 = Alu_output
//1 = data_mem_output
//2,3 = pc + 4

module mem_to_reg (clk,mem_to_reg,alu_result,mem_data,pc_4,selected);
input clk;                  //System clock
input [1:0] mem_to_reg;           //control signal from Control
input [31:0] alu_result;    //Reg[rs2] from Register File
input [31:0] mem_data;      //Immediate from Decoder
input [31:0] pc_4;          //pc from PC add 4 to it
output reg [31:0] selected; //MUX output

always @(posedge clk ) begin
    if(mem_to_reg==1)
        selected = mem_data;
    else if (mem_to_reg==0)
        selected = alu_result;
    else if (mem_to_reg==2 || mem_to_reg==3)
        selected = pc_4 + 3'b100;//pc + 4
end
endmodule

10-Mux_mem_to_reg/mem_to_reg_tb.v
`include "mem_to_reg.v"

module mem_to_reg_tb ();
    //Inputs
    reg clk;
    reg [1:0] mem_to_reg;
    reg [31:0] alu_result;
    reg [31:0] mem_data;
    reg [31:0] pc_4;

    //Outputs
    wire [31:0] selected;

    mem_to_reg uut (clk,mem_to_reg,alu_result,mem_data,pc_4,selected);

    //Clock toggles every 5ns
    always#5 clk=~clk;

    initial begin
        $dumpfile("mem_to_reg.vcd");
        $dumpvars(0,mem_to_reg_tb);

        //Initialize inputs
        clk=0;mem_data=20;alu_result=15;pc_4=4;#10

        mem_to_reg=0;#10 //select alu_result
        mem_to_reg=1;#10 //select mem_data
        mem_to_reg=2;#10 //select pc_4 + 4
        mem_to_reg=3;#10 //select pc_4 + 4



        $finish;
    end
endmodule

10-Mux_mem_to_reg/mem_to_reg.vcd
$date
	Sun May 14 12:14:26 2023
$end
$version
	Icarus Verilog
$end
$timescale
	1ps
$end
$scope module mem_to_reg_tb $end
$var wire 32 ! selected [31:0] $end
$var reg 32 " alu_result [31:0] $end
$var reg 1 # clk $end
$var reg 32 $ mem_data [31:0] $end
$var reg 2 % mem_to_reg [1:0] $end
$var reg 32 & pc_4 [31:0] $end
$scope module uut $end
$var wire 32 ' alu_result [31:0] $end
$var wire 1 # clk $end
$var wire 32 ( mem_data [31:0] $end
$var wire 2 ) mem_to_reg [1:0] $end
$var wire 32 * pc_4 [31:0] $end
$var reg 32 + selected [31:0] $end
$upscope $end
$upscope $end
$enddefinitions $end
#0
$dumpvars
bx +
b100 *
bx )
b10100 (
b1111 '
b100 &
bx %
b10100 $
0#
b1111 "
bx !
$end
#5000
1#
#10000
0#
b0 %
b0 )
#15000
b1111 !
b1111 +
1#
#20000
0#
b1 %
b1 )
#25000
b10100 !
b10100 +
1#
#30000
0#
b10 %
b10 )
#35000
b1000 !
b1000 +
1#
#40000
0#
b11 %
b11 )
