PC/pc.v
`timescale 1ns / 1ps
//PC- Program Counter: for 1024B instruction memory

module pc(clk,reset,branch,jump_offset,pc_out);
input clk;		           	//clock
input reset;               	//reset whole circuit to default
input branch;              	//bool 0=nojump , 1=jump usin jump_offset
input [19:0] jump_offset;  	//immediate -> max 20bits for J type
output reg [9:0] pc_out;	//10bit address -> 2^10 index -> 1024 bytes

always@(posedge clk)begin

	if(reset) 		//reset pc_output
		pc_out <= 0;
	else if(branch) //jump to current address + offset
		pc_out <= pc_out + jump_offset;
	else      		//keep on increasing pc by 4 -> to skip over 1 word ~ 4 bytes
		pc_out <= pc_out + 4;
end
 
endmodule

PC/pc_tb.v
`include "pc.v"

module pc_tb;
    //Inputs
    reg clk,reset,branch;
    reg [19:0] jump_offset;

    //Outputs
    wire [9:0] pc_out;

    pc uut (clk,reset,branch,jump_offset,pc_out);

    //Clock toggles in 5ns
    always#5 clk=~clk;

    initial begin
        $dumpfile("pc.vcd");
        $dumpvars(0,pc_tb);

        //Reset
        clk = 0 ; reset = 1; #10
        reset = 0;

        //PC+4
        branch = 0;#10

        //Jump
        branch = 1;jump_offset = 196;#10
        branch = 1;jump_offset = 800;#10
        
        $finish;
    end
endmodule

PC/pc.vcd
$date
	Sat May 13 02:23:54 2023
$end
$version
	Icarus Verilog
$end
$timescale
	1ps
$end
$scope module pc_tb $end
$var wire 10 ! pc_out [9:0] $end
$var reg 1 " branch $end
$var reg 1 # clk $end
$var reg 20 $ jump_offset [19:0] $end
$var reg 1 % reset $end
$scope module uut $end
$var wire 1 " branch $end
$var wire 1 # clk $end
$var wire 20 & jump_offset [19:0] $end
$var wire 1 % reset $end
$var reg 10 ' pc_out [9:0] $end
$upscope $end
$upscope $end
$enddefinitions $end
#0
$dumpvars
bx '
bx &
1%
bx $
0#
x"
bx !
$end
#5000
b0 !
b0 '
1#
#10000
0#
0"
0%
#15000
b100 !
b100 '
1#
#20000
0#
#25000
b1000 !
b1000 '
1#
#30000
0#
b11000100 $
b11000100 &
1"
#35000
b11001100 !
b11001100 '
1#
#40000
0#
b1100100000 $
b1100100000 &
#45000
b1111101100 !
b1111101100 '
1#
