7-Control_Unit/control.v
`timescale 1ns / 1ps
//control- Control Unit: map opcode to control signals 

module control(clk,opcode,branch,mem_read,mem_write,alu_src,reg_write,mem_to_reg,alu_op);
input clk;                  //System clock
input [6:0] opcode;         //opcode from instruction
output reg branch,mem_read,mem_write,alu_src,reg_write; //control signals
output reg [1:0] mem_to_reg;//control signal
output reg [1:0] alu_op;    //control signal for ALU

parameter r_type = 7'b0110011;//add,sub,and,or
parameter s_type = 7'b0100011;//sw,sb
parameter i_type = 7'b0010011;//addi
parameter l_type = 7'b0000011;//lw,lb
parameter b_type = 7'b1100011;//beq,bge,blt
parameter jal    = 7'b1101111;//jal
parameter jalr   = 7'b1100111;//jalr


always @(posedge clk ) begin
    case(opcode)
    r_type:
    begin
        alu_src = 0;
        mem_to_reg = 2'b00;
        reg_write = 1;
        mem_read = 0;
        mem_write = 0;
        branch = 0;
        alu_op = 2'b10;
	end
    s_type:
    begin
        alu_src = 1;
        mem_to_reg = 2'bx;
        reg_write = 0;
        mem_read = 0;
        mem_write = 1;
        branch = 0;
        alu_op = 2'b00;
	end
    i_type:
    begin
        alu_src = 0;
        mem_to_reg = 2'b0;
        reg_write = 1;
        mem_read = 0;
        mem_write = 0;
        branch = 0;
        alu_op = 2'b00;
	end
    l_type:
    begin
        alu_src = 1;
        mem_to_reg = 2'b01;
        reg_write = 1;
        mem_read = 1;
        mem_write = 0;
        branch = 0;
        alu_op = 2'b00;
	end
    b_type:
    begin
        alu_src = 0;
        mem_to_reg = 2'bx;
        reg_write = 0;
        mem_read = 0;
        mem_write = 0;
        branch = 1;
        alu_op = 2'b01;
	end
    jal:
    begin
        alu_src = 0;
        mem_to_reg = 2'b10;
        reg_write = 1;
        mem_read = 0;
        mem_write = 0;
        branch = 1;//depends 
        alu_op = 2'b11;
	end
    jalr:
    begin
        alu_src = 1;
        mem_to_reg = 2'b11;
        reg_write = 1;
        mem_read = 0;
        mem_write = 0;
        branch = 1;//depends
        alu_op = 2'b11;
	end
    endcase
end
endmodule

7-Control_Unit/control_tb.v
`include "control.v"

module control_tb ();
    //Inputs
    reg clk;
    reg [6:0] opcode;

    //Outputs
    wire branch,mem_read,mem_write,alu_src,reg_write;
    wire [1:0] mem_to_reg;
    wire [1:0] alu_op;    

    control uut (clk,opcode,branch,mem_read,mem_write,alu_src,reg_write,mem_to_reg,alu_op);

    //Clock toggles every 5ns
    always#5 clk=~clk;

    initial begin
        $dumpfile("control.vcd");
        $dumpvars(0,control_tb);

        //Initialize inputs
        clk=0;#10
		
        opcode  = 7'b0110011;#10//add,sub,and,or
        opcode  = 7'b0100011;#10//sw,sb
        opcode  = 7'b0010011;#10//addi
        opcode  = 7'b0000011;#10//lw,lb
        opcode  = 7'b1100011;#10//beq,bge,blt
        opcode  = 7'b1101111;#10//jal
        opcode  = 7'b1100111;#10//jalr
    
		$finish;
    end
endmodule

7-Control_Unit/control.vcd
$date
	Sat May 13 23:40:23 2023
$end
$version
	Icarus Verilog
$end
$timescale
	1ps
$end
$scope module control_tb $end
$var wire 1 ! reg_write $end
$var wire 1 " mem_write $end
$var wire 2 # mem_to_reg [1:0] $end
$var wire 1 $ mem_read $end
$var wire 1 % branch $end
$var wire 1 & alu_src $end
$var wire 2 ' alu_op [1:0] $end
$var reg 1 ( clk $end
$var reg 7 ) opcode [6:0] $end
$scope module uut $end
$var wire 1 ( clk $end
$var wire 7 * opcode [6:0] $end
$var reg 2 + alu_op [1:0] $end
$var reg 1 & alu_src $end
$var reg 1 % branch $end
$var reg 1 $ mem_read $end
$var reg 2 , mem_to_reg [1:0] $end
$var reg 1 " mem_write $end
$var reg 1 ! reg_write $end
$upscope $end
$upscope $end
$enddefinitions $end
#0
$dumpvars
bx ,
bx +
bx *
bx )
0(
bx '
x&
x%
x$
bx #
x"
x!
$end
#5000
1(
#10000
0(
b110011 )
b110011 *
#15000
b10 '
b10 +
0%
0"
0$
1!
b0 #
b0 ,
0&
1(
#20000
0(
b100011 )
b100011 *
#25000
b0 '
b0 +
1"
0!
bx #
bx ,
1&
1(
#30000
0(
b10011 )
b10011 *
#35000
0"
1!
b0 #
b0 ,
0&
1(
#40000
0(
b11 )
b11 *
#45000
1$
b1 #
b1 ,
1&
1(
#50000
0(
b1100011 )
b1100011 *
#55000
b1 '
b1 +
1%
0$
0!
bx #
bx ,
0&
1(
#60000
0(
b1101111 )
b1101111 *
#65000
b11 '
b11 +
1!
b0 #
b0 ,
1(
#70000
0(
b1100111 )
b1100111 *
#75000
1&
1(
