ALU/alu.v
`timescale 1ns / 1ps
//alu- Arithmetic Logic Unit: perform operations based on ISA.txt
// 
// ALU control | Function
// -----------------------------
//         000    Bitwise-AND
//         001    Bitwise-OR
//         010	  Add (A+B)
//         011    Subtract (A-B)
//         100	  Less than (A<B)
//         101    Greater than or equal (A>=B)
//         110    Equal (A==B)
//         111    xxxxxxxx
module alu (clk,in1,in2,result,alu_control,zero_flag);
input clk;                      //sytem clock
input [31:0] in1,in2;           //data inputs
input[2:0] alu_control;         //control for operation selection
output reg [31:0] result;   //output of ALU
output reg zero_flag;                //flag if beq,blt,bge TRUE

always @(posedge clk ) begin
        // Operating based on control input
        case(alu_control)

            3'b000: result = in1&in2; //AND
            3'b001: result = in1|in2; //OR
            3'b010: result = in1+in2; //Add
            3'b011: result = in1-in2; //Sub
            3'b100:                       //A<B
            begin 
                if(in1<in2)
                    result = 0;
                else
                    result = 32'bx;
            end
            3'b101: 
            begin 
                if(in1>=in2)            //A>=B
                    result = 0;
                else
                    result = 32'bx;
            end
            3'b011:                     //A==B
            begin 
                if(in1==in2)
                    result = 0;
                else
                    result = 32'bx;
            end
        endcase

        // Setting Zero_flag if ALU_result is zero
        if (result == 0)
            zero_flag = 1'b1;
        else
            zero_flag = 1'b0;
end
    
endmodule

ALU/alu_tb.v
`include "alu.v"

module alu_tb ();
    //Inputs
    reg clk;                      
    reg [31:0] in1,in2;          
    reg [2:0] alu_control;

    //Outputs
    wire [31:0] result;
    wire zero_flag;

    alu uut (clk,in1,in2,result,alu_control,zero_flag);

    //Clock toggles every 5ns
    always#5 clk=~clk;

    initial begin
        $dumpfile("alu.vcd");
        $dumpvars(0,alu_tb);

        //initialize inputs
        clk=0;#10

        in1=2;in2=3;

        alu_control=0;#10//AND
        alu_control=1;#10//OR
        alu_control=2;#10//Add
        alu_control=3;#10//sub
        alu_control=4;#10//<
        alu_control=5;#10//>=
        alu_control=6;#10//==

        $finish;
    end

endmodule

ALU/alu.vcd
$date
	Sat May 13 19:05:57 2023
$end
$version
	Icarus Verilog
$end
$timescale
	1ps
$end
$scope module alu_tb $end
$var wire 1 ! zero_flag $end
$var wire 32 " result [31:0] $end
$var reg 3 # alu_control [2:0] $end
$var reg 1 $ clk $end
$var reg 32 % in1 [31:0] $end
$var reg 32 & in2 [31:0] $end
$scope module uut $end
$var wire 3 ' alu_control [2:0] $end
$var wire 1 $ clk $end
$var wire 32 ( in1 [31:0] $end
$var wire 32 ) in2 [31:0] $end
$var reg 32 * result [31:0] $end
$var reg 1 ! zero_flag $end
$upscope $end
$upscope $end
$enddefinitions $end
#0
$dumpvars
bx *
bx )
bx (
bx '
bx &
bx %
0$
bx #
bx "
x!
$end
#5000
0!
1$
#10000
0$
b0 #
b0 '
b11 &
b11 )
b10 %
b10 (
#15000
b10 "
b10 *
1$
#20000
0$
b1 #
b1 '
#25000
b11 "
b11 *
1$
#30000
0$
b10 #
b10 '
#35000
b101 "
b101 *
1$
#40000
0$
b11 #
b11 '
#45000
b11111111111111111111111111111111 "
b11111111111111111111111111111111 *
1$
#50000
0$
b100 #
b100 '
#55000
1!
b0 "
b0 *
1$
#60000
0$
b101 #
b101 '
#65000
0!
bx "
bx *
1$
#70000
0$
b110 #
b110 '
